{
  "guncellemeZamani": "2026-07-21T07:50:06+00:00",
  "kaynak": "google-flights (Turkish Airlines filtreli)",
  "sorgulananBolge": "hepsi",
  "hucreSayisi": 52,
  "hataSayisi": 22,
  "sonuclar": [
    {
      "rota": "SAW → BER",
      "kalkis": "SAW",
      "varis": "BER",
      "seyahatTipi": "R",
      "gidisTarihi": "2026-08-28",
      "bolge": "Avrupa",
      "donusTarihi": "2026-09-04",
      "durum": "hata",
      "detay": "TypeError: 'NoneType' object is not subscriptable"
    },
    {
      "rota": "SAW → BER",
      "kalkis": "SAW",
      "varis": "BER",
      "seyahatTipi": "R",
      "gidisTarihi": "2026-09-03",
      "bolge": "Avrupa",
      "donusTarihi": "2026-09-10",
      "durum": "hata",
      "detay": "TypeError: 'NoneType' object is not subscriptable"
    },
    {
      "rota": "SAW → MUC",
      "kalkis": "SAW",
      "varis": "MUC",
      "seyahatTipi": "R",
      "gidisTarihi": "2026-08-28",
      "bolge": "Avrupa",
      "donusTarihi": "2026-09-04",
      "durum": "hata",
      "detay": "TypeError: 'NoneType' object is not subscriptable"
    },
    {
      "rota": "SAW → MUC",
      "kalkis": "SAW",
      "varis": "MUC",
      "seyahatTipi": "R",
      "gidisTarihi": "2026-09-03",
      "bolge": "Avrupa",
      "donusTarihi": "2026-09-10",
      "durum": "hata",
      "detay": "TypeError: 'NoneType' object is not subscriptable"
    },
    {
      "rota": "SAW → FRA",
      "kalkis": "SAW",
      "varis": "FRA",
      "seyahatTipi": "R",
      "gidisTarihi": "2026-08-28",
      "bolge": "Avrupa",
      "donusTarihi": "2026-09-04",
      "durum": "hata",
      "detay": "TypeError: 'NoneType' object is not subscriptable"
    },
    {
      "rota": "SAW → FRA",
      "kalkis": "SAW",
      "varis": "FRA",
      "seyahatTipi": "R",
      "gidisTarihi": "2026-09-03",
      "bolge": "Avrupa",
      "donusTarihi": "2026-09-10",
      "durum": "hata",
      "detay": "TypeError: 'NoneType' object is not subscriptable"
    },
    {
      "rota": "SAW → VIE",
      "kalkis": "SAW",
      "varis": "VIE",
      "seyahatTipi": "R",
      "gidisTarihi": "2026-08-28",
      "bolge": "Avrupa",
      "donusTarihi": "2026-09-04",
      "durum": "hata",
      "detay": "TypeError: 'NoneType' object is not subscriptable"
    },
    {
      "rota": "SAW → VIE",
      "kalkis": "SAW",
      "varis": "VIE",
      "seyahatTipi": "R",
      "gidisTarihi": "2026-09-03",
      "bolge": "Avrupa",
      "donusTarihi": "2026-09-10",
      "durum": "hata",
      "detay": "TypeError: 'NoneType' object is not subscriptable"
    },
    {
      "rota": "IST → MIA",
      "kalkis": "IST",
      "varis": "MIA",
      "seyahatTipi": "R",
      "gidisTarihi": "2026-08-28",
      "bolge": "Amerika",
      "donusTarihi": "2026-09-04",
      "tutar": 60742.0,
      "paraBirimi": "TRY",
      "adayFiyatSayisi": 2,
      "durum": "ok",
      "aktarma": 0
    },
    {
      "rota": "IST → MIA",
      "kalkis": "IST",
      "varis": "MIA",
      "seyahatTipi": "R",
      "gidisTarihi": "2026-09-03",
      "bolge": "Amerika",
      "donusTarihi": "2026-09-10",
      "tutar": 41914.0,
      "paraBirimi": "TRY",
      "adayFiyatSayisi": 2,
      "durum": "ok",
      "aktarma": 0
    },
    {
      "rota": "IST → PVG",
      "kalkis": "IST",
      "varis": "PVG",
      "seyahatTipi": "R",
      "gidisTarihi": "2026-08-28",
      "bolge": "Asya",
      "donusTarihi": "2026-09-04",
      "tutar": 45170.0,
      "paraBirimi": "TRY",
      "adayFiyatSayisi": 2,
      "durum": "ok",
      "aktarma": 0
    },
    {
      "rota": "IST → PVG",
      "kalkis": "IST",
      "varis": "PVG",
      "seyahatTipi": "R",
      "gidisTarihi": "2026-09-03",
      "bolge": "Asya",
      "donusTarihi": "2026-09-10",
      "tutar": 42346.0,
      "paraBirimi": "TRY",
      "adayFiyatSayisi": 2,
      "durum": "ok",
      "aktarma": 0
    },
    {
      "rota": "IST → HGK",
      "kalkis": "IST",
      "varis": "HGK",
      "seyahatTipi": "R",
      "gidisTarihi": "2026-08-28",
      "bolge": "Asya",
      "donusTarihi": "2026-09-04",
      "durum": "hata",
      "detay": "IndexError: list index out of range"
    },
    {
      "rota": "IST → HGK",
      "kalkis": "IST",
      "varis": "HGK",
      "seyahatTipi": "R",
      "gidisTarihi": "2026-09-03",
      "bolge": "Asya",
      "donusTarihi": "2026-09-10",
      "durum": "hata",
      "detay": "IndexError: list index out of range"
    },
    {
      "rota": "IST → PEK",
      "kalkis": "IST",
      "varis": "PEK",
      "seyahatTipi": "R",
      "gidisTarihi": "2026-08-28",
      "bolge": "Asya",
      "donusTarihi": "2026-09-04",
      "tutar": 38580.0,
      "paraBirimi": "TRY",
      "adayFiyatSayisi": 3,
      "durum": "ok",
      "aktarma": 0
    },
    {
      "rota": "IST → PEK",
      "kalkis": "IST",
      "varis": "PEK",
      "seyahatTipi": "R",
      "gidisTarihi": "2026-09-03",
      "bolge": "Asya",
      "donusTarihi": "2026-09-10",
      "tutar": 40228.0,
      "paraBirimi": "TRY",
      "adayFiyatSayisi": 3,
      "durum": "ok",
      "aktarma": 0
    },
    {
      "rota": "IST → CAN",
      "kalkis": "IST",
      "varis": "CAN",
      "seyahatTipi": "R",
      "gidisTarihi": "2026-08-28",
      "bolge": "Asya",
      "donusTarihi": "2026-09-04",
      "tutar": 32979.0,
      "paraBirimi": "TRY",
      "adayFiyatSayisi": 2,
      "durum": "ok",
      "aktarma": 0
    },
    {
      "rota": "IST → CAN",
      "kalkis": "IST",
      "varis": "CAN",
      "seyahatTipi": "R",
      "gidisTarihi": "2026-09-03",
      "bolge": "Asya",
      "donusTarihi": "2026-09-10",
      "tutar": 32979.0,
      "paraBirimi": "TRY",
      "adayFiyatSayisi": 2,
      "durum": "ok",
      "aktarma": 0
    },
    {
      "rota": "IST → NRT",
      "kalkis": "IST",
      "varis": "NRT",
      "seyahatTipi": "R",
      "gidisTarihi": "2026-08-28",
      "bolge": "Asya",
      "donusTarihi": "2026-09-04",
      "tutar": 70712.0,
      "paraBirimi": "TRY",
      "adayFiyatSayisi": 1,
      "durum": "ok",
      "aktarma": 0
    },
    {
      "rota": "IST → NRT",
      "kalkis": "IST",
      "varis": "NRT",
      "seyahatTipi": "R",
      "gidisTarihi": "2026-09-03",
      "bolge": "Asya",
      "donusTarihi": "2026-09-10",
      "tutar": 59510.0,
      "paraBirimi": "TRY",
      "adayFiyatSayisi": 2,
      "durum": "ok",
      "aktarma": 0
    },
    {
      "rota": "IST → HND",
      "kalkis": "IST",
      "varis": "HND",
      "seyahatTipi": "R",
      "gidisTarihi": "2026-08-28",
      "bolge": "Asya",
      "donusTarihi": "2026-09-04",
      "tutar": 86420.0,
      "paraBirimi": "TRY",
      "adayFiyatSayisi": 1,
      "durum": "ok",
      "aktarma": 0
    },
    {
      "rota": "IST → HND",
      "kalkis": "IST",
      "varis": "HND",
      "seyahatTipi": "R",
      "gidisTarihi": "2026-09-03",
      "bolge": "Asya",
      "donusTarihi": "2026-09-10",
      "tutar": 81336.0,
      "paraBirimi": "TRY",
      "adayFiyatSayisi": 1,
      "durum": "ok",
      "aktarma": 0
    },
    {
      "rota": "IST → KIX",
      "kalkis": "IST",
      "varis": "KIX",
      "seyahatTipi": "R",
      "gidisTarihi": "2026-08-28",
      "bolge": "Asya",
      "donusTarihi": "2026-09-04",
      "tutar": 94854.0,
      "paraBirimi": "TRY",
      "adayFiyatSayisi": 1,
      "durum": "ok",
      "aktarma": 0
    },
    {
      "rota": "IST → KIX",
      "kalkis": "IST",
      "varis": "KIX",
      "seyahatTipi": "R",
      "gidisTarihi": "2026-09-03",
      "bolge": "Asya",
      "donusTarihi": "2026-09-10",
      "tutar": 70001.0,
      "paraBirimi": "TRY",
      "adayFiyatSayisi": 1,
      "durum": "ok",
      "aktarma": 0
    },
    {
      "rota": "IST → ICN",
      "kalkis": "IST",
      "varis": "ICN",
      "seyahatTipi": "R",
      "gidisTarihi": "2026-08-28",
      "bolge": "Asya",
      "donusTarihi": "2026-09-04",
      "tutar": 52270.0,
      "paraBirimi": "TRY",
      "adayFiyatSayisi": 2,
      "durum": "ok",
      "aktarma": 0
    },
    {
      "rota": "IST → ICN",
      "kalkis": "IST",
      "varis": "ICN",
      "seyahatTipi": "R",
      "gidisTarihi": "2026-09-03",
      "bolge": "Asya",
      "donusTarihi": "2026-09-10",
      "tutar": 53447.0,
      "paraBirimi": "TRY",
      "adayFiyatSayisi": 3,
      "durum": "ok",
      "aktarma": 0
    },
    {
      "rota": "IST → SGN",
      "kalkis": "IST",
      "varis": "SGN",
      "seyahatTipi": "R",
      "gidisTarihi": "2026-08-28",
      "bolge": "Asya",
      "donusTarihi": "2026-09-04",
      "tutar": 58053.0,
      "paraBirimi": "TRY",
      "adayFiyatSayisi": 1,
      "durum": "ok",
      "aktarma": 0
    },
    {
      "rota": "IST → SGN",
      "kalkis": "IST",
      "varis": "SGN",
      "seyahatTipi": "R",
      "gidisTarihi": "2026-09-03",
      "bolge": "Asya",
      "donusTarihi": "2026-09-10",
      "tutar": 54993.0,
      "paraBirimi": "TRY",
      "adayFiyatSayisi": 1,
      "durum": "ok",
      "aktarma": 0
    },
    {
      "rota": "IST → JFK",
      "kalkis": "IST",
      "varis": "JFK",
      "seyahatTipi": "R",
      "gidisTarihi": "2026-08-28",
      "bolge": "Amerika",
      "donusTarihi": "2026-09-04",
      "tutar": 67097.0,
      "paraBirimi": "TRY",
      "adayFiyatSayisi": 4,
      "durum": "ok",
      "aktarma": 0
    },
    {
      "rota": "IST → JFK",
      "kalkis": "IST",
      "varis": "JFK",
      "seyahatTipi": "R",
      "gidisTarihi": "2026-09-03",
      "bolge": "Amerika",
      "donusTarihi": "2026-09-10",
      "tutar": 46622.0,
      "paraBirimi": "TRY",
      "adayFiyatSayisi": 4,
      "durum": "ok",
      "aktarma": 0
    },
    {
      "rota": "IST → ORD",
      "kalkis": "IST",
      "varis": "ORD",
      "seyahatTipi": "R",
      "gidisTarihi": "2026-08-28",
      "bolge": "Amerika",
      "donusTarihi": "2026-09-04",
      "tutar": 49211.0,
      "paraBirimi": "TRY",
      "adayFiyatSayisi": 2,
      "durum": "ok",
      "aktarma": 0
    },
    {
      "rota": "IST → ORD",
      "kalkis": "IST",
      "varis": "ORD",
      "seyahatTipi": "R",
      "gidisTarihi": "2026-09-03",
      "bolge": "Amerika",
      "donusTarihi": "2026-09-10",
      "tutar": 37396.0,
      "paraBirimi": "TRY",
      "adayFiyatSayisi": 2,
      "durum": "ok",
      "aktarma": 0
    },
    {
      "rota": "IST → BOS",
      "kalkis": "IST",
      "varis": "BOS",
      "seyahatTipi": "R",
      "gidisTarihi": "2026-08-28",
      "bolge": "Amerika",
      "donusTarihi": "2026-09-04",
      "tutar": 89362.0,
      "paraBirimi": "TRY",
      "adayFiyatSayisi": 1,
      "durum": "ok",
      "aktarma": 0
    },
    {
      "rota": "IST → BOS",
      "kalkis": "IST",
      "varis": "BOS",
      "seyahatTipi": "R",
      "gidisTarihi": "2026-09-03",
      "bolge": "Amerika",
      "donusTarihi": "2026-09-10",
      "tutar": 55094.0,
      "paraBirimi": "TRY",
      "adayFiyatSayisi": 1,
      "durum": "ok",
      "aktarma": 0
    },
    {
      "rota": "IST → DWF",
      "kalkis": "IST",
      "varis": "DWF",
      "seyahatTipi": "R",
      "gidisTarihi": "2026-08-28",
      "bolge": "Amerika",
      "donusTarihi": "2026-09-04",
      "durum": "hata",
      "detay": "IndexError: list index out of range"
    },
    {
      "rota": "IST → DWF",
      "kalkis": "IST",
      "varis": "DWF",
      "seyahatTipi": "R",
      "gidisTarihi": "2026-09-03",
      "bolge": "Amerika",
      "donusTarihi": "2026-09-10",
      "durum": "hata",
      "detay": "IndexError: list index out of range"
    },
    {
      "rota": "IST → IAH",
      "kalkis": "IST",
      "varis": "IAH",
      "seyahatTipi": "R",
      "gidisTarihi": "2026-08-28",
      "bolge": "Amerika",
      "donusTarihi": "2026-09-04",
      "tutar": 50857.0,
      "paraBirimi": "TRY",
      "adayFiyatSayisi": 2,
      "durum": "ok",
      "aktarma": 0
    },
    {
      "rota": "IST → IAH",
      "kalkis": "IST",
      "varis": "IAH",
      "seyahatTipi": "R",
      "gidisTarihi": "2026-09-03",
      "bolge": "Amerika",
      "donusTarihi": "2026-09-10",
      "tutar": 37207.0,
      "paraBirimi": "TRY",
      "adayFiyatSayisi": 1,
      "durum": "ok",
      "aktarma": 0
    },
    {
      "rota": "IST → IAD",
      "kalkis": "IST",
      "varis": "IAD",
      "seyahatTipi": "R",
      "gidisTarihi": "2026-08-28",
      "bolge": "Amerika",
      "donusTarihi": "2026-09-04",
      "tutar": 59330.0,
      "paraBirimi": "TRY",
      "adayFiyatSayisi": 2,
      "durum": "ok",
      "aktarma": 0
    },
    {
      "rota": "IST → IAD",
      "kalkis": "IST",
      "varis": "IAD",
      "seyahatTipi": "R",
      "gidisTarihi": "2026-09-03",
      "bolge": "Amerika",
      "donusTarihi": "2026-09-10",
      "tutar": 39043.0,
      "paraBirimi": "TRY",
      "adayFiyatSayisi": 2,
      "durum": "ok",
      "aktarma": 0
    },
    {
      "rota": "IST → LAS",
      "kalkis": "IST",
      "varis": "LAS",
      "seyahatTipi": "R",
      "gidisTarihi": "2026-08-28",
      "bolge": "Amerika",
      "donusTarihi": "2026-09-04",
      "durum": "hata",
      "detay": "TypeError: 'NoneType' object is not subscriptable"
    },
    {
      "rota": "IST → LAS",
      "kalkis": "IST",
      "varis": "LAS",
      "seyahatTipi": "R",
      "gidisTarihi": "2026-09-03",
      "bolge": "Amerika",
      "donusTarihi": "2026-09-10",
      "durum": "hata",
      "detay": "TypeError: 'NoneType' object is not subscriptable"
    },
    {
      "rota": "IST → SDU",
      "kalkis": "IST",
      "varis": "SDU",
      "seyahatTipi": "R",
      "gidisTarihi": "2026-08-28",
      "bolge": "Amerika",
      "donusTarihi": "2026-09-04",
      "durum": "hata",
      "detay": "TypeError: 'NoneType' object is not subscriptable"
    },
    {
      "rota": "IST → SDU",
      "kalkis": "IST",
      "varis": "SDU",
      "seyahatTipi": "R",
      "gidisTarihi": "2026-09-03",
      "bolge": "Amerika",
      "donusTarihi": "2026-09-10",
      "durum": "hata",
      "detay": "TypeError: 'NoneType' object is not subscriptable"
    },
    {
      "rota": "IST → EZE",
      "kalkis": "IST",
      "varis": "EZE",
      "seyahatTipi": "R",
      "gidisTarihi": "2026-08-28",
      "bolge": "Amerika",
      "donusTarihi": "2026-09-04",
      "durum": "hata",
      "detay": "TypeError: 'NoneType' object is not subscriptable"
    },
    {
      "rota": "IST → EZE",
      "kalkis": "IST",
      "varis": "EZE",
      "seyahatTipi": "R",
      "gidisTarihi": "2026-09-03",
      "bolge": "Amerika",
      "donusTarihi": "2026-09-10",
      "durum": "hata",
      "detay": "TypeError: 'NoneType' object is not subscriptable"
    },
    {
      "rota": "IST → HAV",
      "kalkis": "IST",
      "varis": "HAV",
      "seyahatTipi": "R",
      "gidisTarihi": "2026-08-28",
      "bolge": "Amerika",
      "donusTarihi": "2026-09-04",
      "durum": "hata",
      "detay": "TypeError: 'NoneType' object is not subscriptable"
    },
    {
      "rota": "IST → HAV",
      "kalkis": "IST",
      "varis": "HAV",
      "seyahatTipi": "R",
      "gidisTarihi": "2026-09-03",
      "bolge": "Amerika",
      "donusTarihi": "2026-09-10",
      "durum": "hata",
      "detay": "TypeError: 'NoneType' object is not subscriptable"
    },
    {
      "rota": "SAW → AMS",
      "kalkis": "SAW",
      "varis": "AMS",
      "seyahatTipi": "R",
      "gidisTarihi": "2026-08-28",
      "bolge": "Avrupa",
      "donusTarihi": "2026-09-04",
      "durum": "hata",
      "detay": "TypeError: 'NoneType' object is not subscriptable"
    },
    {
      "rota": "SAW → AMS",
      "kalkis": "SAW",
      "varis": "AMS",
      "seyahatTipi": "R",
      "gidisTarihi": "2026-09-03",
      "bolge": "Avrupa",
      "donusTarihi": "2026-09-10",
      "durum": "hata",
      "detay": "TypeError: 'NoneType' object is not subscriptable"
    },
    {
      "rota": "IST → FCO",
      "kalkis": "IST",
      "varis": "FCO",
      "seyahatTipi": "R",
      "gidisTarihi": "2026-08-28",
      "bolge": "Avrupa",
      "donusTarihi": "2026-09-04",
      "tutar": 31295.0,
      "paraBirimi": "TRY",
      "adayFiyatSayisi": 4,
      "durum": "ok",
      "aktarma": 0
    },
    {
      "rota": "IST → FCO",
      "kalkis": "IST",
      "varis": "FCO",
      "seyahatTipi": "R",
      "gidisTarihi": "2026-09-03",
      "bolge": "Avrupa",
      "donusTarihi": "2026-09-10",
      "tutar": 28189.0,
      "paraBirimi": "TRY",
      "adayFiyatSayisi": 4,
      "durum": "ok",
      "aktarma": 0
    }
  ]
}